daytona_daemon_api_client_async/__init__.py
daytona_daemon_api_client_async/api_client.py
daytona_daemon_api_client_async/api_response.py
daytona_daemon_api_client_async/configuration.py
daytona_daemon_api_client_async/exceptions.py
daytona_daemon_api_client_async/py.typed
daytona_daemon_api_client_async/rest.py
daytona_daemon_api_client_async/api/__init__.py
daytona_daemon_api_client_async/api/computer_use_api.py
daytona_daemon_api_client_async/api/file_system_api.py
daytona_daemon_api_client_async/api/git_api.py
daytona_daemon_api_client_async/api/info_api.py
daytona_daemon_api_client_async/api/lsp_api.py
daytona_daemon_api_client_async/api/port_api.py
daytona_daemon_api_client_async/api/process_api.py
daytona_daemon_api_client_async/models/__init__.py
daytona_daemon_api_client_async/models/command.py
daytona_daemon_api_client_async/models/completion_context.py
daytona_daemon_api_client_async/models/completion_item.py
daytona_daemon_api_client_async/models/completion_list.py
daytona_daemon_api_client_async/models/computer_use_start_response.py
daytona_daemon_api_client_async/models/computer_use_status_response.py
daytona_daemon_api_client_async/models/computer_use_stop_response.py
daytona_daemon_api_client_async/models/create_session_request.py
daytona_daemon_api_client_async/models/display_info.py
daytona_daemon_api_client_async/models/display_info_response.py
daytona_daemon_api_client_async/models/execute_request.py
daytona_daemon_api_client_async/models/execute_response.py
daytona_daemon_api_client_async/models/file_info.py
daytona_daemon_api_client_async/models/file_status.py
daytona_daemon_api_client_async/models/git_add_request.py
daytona_daemon_api_client_async/models/git_branch_request.py
daytona_daemon_api_client_async/models/git_checkout_request.py
daytona_daemon_api_client_async/models/git_clone_request.py
daytona_daemon_api_client_async/models/git_commit_info.py
daytona_daemon_api_client_async/models/git_commit_request.py
daytona_daemon_api_client_async-0.102.0rc1.dist-info/licenses/LICENSE
daytona_daemon_api_client_async-0.102.0rc1.dist-info/METADATA
daytona_daemon_api_client_async-0.102.0rc1.dist-info/WHEEL
daytona_daemon_api_client_async-0.102.0rc1.dist-info/top_level.txt
daytona_daemon_api_client_async-0.102.0rc1.dist-info/RECORD
